fds/__init__.py
fds/sdk/__init__.py
fds/sdk/SPAREngine/__init__.py
fds/sdk/SPAREngine/api_client.py
fds/sdk/SPAREngine/configuration.py
fds/sdk/SPAREngine/exceptions.py
fds/sdk/SPAREngine/model_utils.py
fds/sdk/SPAREngine/rest.py
fds/sdk/SPAREngine/api/__init__.py
fds/sdk/SPAREngine/api/accounts_api.py
fds/sdk/SPAREngine/api/benchmarks_api.py
fds/sdk/SPAREngine/api/components_api.py
fds/sdk/SPAREngine/api/currencies_api.py
fds/sdk/SPAREngine/api/documents_api.py
fds/sdk/SPAREngine/api/frequencies_api.py
fds/sdk/SPAREngine/api/spar_calculations_api.py
fds/sdk/SPAREngine/api/spar_peer_universe_api.py
fds/sdk/SPAREngine/apis/__init__.py
fds/sdk/SPAREngine/model/__init__.py
fds/sdk/SPAREngine/model/account_directories.py
fds/sdk/SPAREngine/model/account_directories_root.py
fds/sdk/SPAREngine/model/calculation_meta.py
fds/sdk/SPAREngine/model/calculation_status.py
fds/sdk/SPAREngine/model/calculation_status_meta.py
fds/sdk/SPAREngine/model/calculation_status_root.py
fds/sdk/SPAREngine/model/calculation_unit_status.py
fds/sdk/SPAREngine/model/calculation_unit_status_meta.py
fds/sdk/SPAREngine/model/calculations_summary.py
fds/sdk/SPAREngine/model/calculations_summary_root.py
fds/sdk/SPAREngine/model/client_error_response.py
fds/sdk/SPAREngine/model/component_summary.py
fds/sdk/SPAREngine/model/component_summary_root.py
fds/sdk/SPAREngine/model/currency.py
fds/sdk/SPAREngine/model/currency_root.py
fds/sdk/SPAREngine/model/document_directories.py
fds/sdk/SPAREngine/model/document_directories_root.py
fds/sdk/SPAREngine/model/error.py
fds/sdk/SPAREngine/model/error_source.py
fds/sdk/SPAREngine/model/frequency.py
fds/sdk/SPAREngine/model/frequency_root.py
fds/sdk/SPAREngine/model/object_root.py
fds/sdk/SPAREngine/model/pagination_info.py
fds/sdk/SPAREngine/model/pagination_meta.py
fds/sdk/SPAREngine/model/return_type.py
fds/sdk/SPAREngine/model/spar_accounts.py
fds/sdk/SPAREngine/model/spar_accounts_root.py
fds/sdk/SPAREngine/model/spar_benchmark.py
fds_sdk_sparengine-2.2.0.dist-info/licenses/LICENSE
fds_sdk_sparengine-2.2.0.dist-info/METADATA
fds_sdk_sparengine-2.2.0.dist-info/WHEEL
fds_sdk_sparengine-2.2.0.dist-info/top_level.txt
fds_sdk_sparengine-2.2.0.dist-info/RECORD
